utilitysentry/__init__.py
utilitysentry/comman/constants.py
utilitysentry/comman/utility_default_logger.py
utilitysentry/config/__init__.py
utilitysentry/config/config_exception.py
utilitysentry/config/utility_config.py
utilitysentry/exception/__init__.py
utilitysentry/exception/utility_exception.py
utilitysentry/logger/__init__.py
utilitysentry/logger/logger_exception.py
utilitysentry/logger/utility_logger.py
utilitysentry/response/__init__.py
utilitysentry/response/response_codes.py
utilitysentry/response/utility_response.py
utilitysentry/validation/__init__.py
utilitysentry/validation/utility_validator.py
utilitysentry/validation/validation_exception.py
utilitysentry/validation/helper/__init__.py
utilitysentry/validation/helper/base_validation.py
utilitysentry/validation/helper/validation_helper.py
utilitysentry/validation/helper/validation_message.py
utilitysentry/validation/validator_class/__init__.py
utilitysentry/validation/validator_class/boolean/boolean_validator.py
utilitysentry/validation/validator_class/datetime/datetime_validator.py
utilitysentry/validation/validator_class/dictionary/dictionary_validator.py
utilitysentry/validation/validator_class/email/email_validator.py
utilitysentry/validation/validator_class/list/list_validator.py
utilitysentry/validation/validator_class/number/float_validator.py
utilitysentry/validation/validator_class/number/integer_validator.py
utilitysentry/validation/validator_class/password/password_validator.py
utilitysentry/validation/validator_class/phone/phone_validator.py
utilitysentry/validation/validator_class/regex/regex_validator.py
utilitysentry/validation/validator_class/set/set_validator.py
utilitysentry/validation/validator_class/string/is_numeric_validator.py
utilitysentry/validation/validator_class/string/string_validator.py
utilitysentry/validation/validator_class/tuple/tuple_validator.py
utilitysentry/validation/validator_class/uuid/uuid_validator.py
utility_sentry-1.0.1.dist-info/LICENSE
utility_sentry-1.0.1.dist-info/METADATA
utility_sentry-1.0.1.dist-info/WHEEL
utility_sentry-1.0.1.dist-info/top_level.txt
utility_sentry-1.0.1.dist-info/RECORD
