Metadata-Version: 2.1
Name: utility-sentry
Version: 1.0.1
Summary: Utility Sentry provides common components for software development to reduce developers efforts.
Home-page: UNKNOWN
Author: Ankit Prajapat
Author-email: ankitprajapat948@gmail.com
License: UNKNOWN
Platform: UNKNOWN
Classifier: Programming Language :: Python :: 3
Classifier: License :: OSI Approved :: MIT License
Classifier: Operating System :: OS Independent
Requires-Dist: PyYAML
